{"Success":{"submission":{"_id":"64abc9d767169bacdb5f2b32","problem_id":62,"user_id":"64a3a7de8c685313d1c60d9d","score":{"Success":314538699.0},"submitted_at":"2023-07-10T09:05:27.403549275Z"},"contents":"{\"placements\":[{\"x\":3971,\"y\":4703},{\"x\":4811,\"y\":4353},{\"x\":4301,\"y\":6053},{\"x\":3971,\"y\":5103},{\"x\":4311,\"y\":6053},{\"x\":4321,\"y\":6053},{\"x\":4811,\"y\":4343},{\"x\":3971,\"y\":4723},{\"x\":3971,\"y\":5413},{\"x\":4811,\"y\":4303},{\"x\":3971,\"y\":4753},{\"x\":3971,\"y\":4003},{\"x\":4291,\"y\":6053},{\"x\":4811,\"y\":4313},{\"x\":4811,\"y\":5033},{\"x\":3971,\"y\":4683},{\"x\":4281,\"y\":6053},{\"x\":3971,\"y\":4713},{\"x\":3971,\"y\":3993},{\"x\":4811,\"y\":4293},{\"x\":4811,\"y\":4333},{\"x\":4271,\"y\":6053},{\"x\":4261,\"y\":6053},{\"x\":4811,\"y\":4643},{\"x\":4811,\"y\":4323},{\"x\":3971,\"y\":3773},{\"x\":4811,\"y\":5333},{\"x\":4811,\"y\":4633},{\"x\":4811,\"y\":4393},{\"x\":4811,\"y\":4653},{\"x\":3971,\"y\":4693},{\"x\":3971,\"y\":5113},{\"x\":3971,\"y\":5003},{\"x\":3971,\"y\":3983},{\"x\":4811,\"y\":4383},{\"x\":4251,\"y\":6053},{\"x\":4241,\"y\":6053},{\"x\":4811,\"y\":4403},{\"x\":4811,\"y\":4443},{\"x\":4811,\"y\":4463},{\"x\":4811,\"y\":4433},{\"x\":4811,\"y\":4423},{\"x\":3971,\"y\":5403},{\"x\":4811,\"y\":5043},{\"x\":4231,\"y\":6053},{\"x\":4221,\"y\":6053},{\"x\":4211,\"y\":6053},{\"x\":4201,\"y\":6053},{\"x\":4811,\"y\":4453},{\"x\":4811,\"y\":5323},{\"x\":3971,\"y\":5123},{\"x\":4811,\"y\":5433},{\"x\":4811,\"y\":5053},{\"x\":4811,\"y\":5063},{\"x\":4811,\"y\":5313},{\"x\":4811,\"y\":4413},{\"x\":4811,\"y\":4663},{\"x\":3971,\"y\":5133},{\"x\":4191,\"y\":6053},{\"x\":4811,\"y\":4363},{\"x\":3971,\"y\":5393},{\"x\":3971,\"y\":3973},{\"x\":4811,\"y\":5073},{\"x\":4811,\"y\":4673},{\"x\":4811,\"y\":5303},{\"x\":4811,\"y\":4373},{\"x\":3971,\"y\":5143},{\"x\":4181,\"y\":6053},{\"x\":4811,\"y\":5083},{\"x\":4811,\"y\":4483},{\"x\":3971,\"y\":5383},{\"x\":4811,\"y\":5293},{\"x\":4811,\"y\":4473},{\"x\":3971,\"y\":5153},{\"x\":4811,\"y\":4533},{\"x\":4811,\"y\":4683},{\"x\":4811,\"y\":4733},{\"x\":4811,\"y\":4543},{\"x\":4811,\"y\":4513},{\"x\":4811,\"y\":4743},{\"x\":4811,\"y\":4553},{\"x\":4811,\"y\":4713},{\"x\":4811,\"y\":4703},{\"x\":4811,\"y\":4283},{\"x\":4811,\"y\":5423},{\"x\":4171,\"y\":6053},{\"x\":3971,\"y\":3963},{\"x\":3971,\"y\":5373},{\"x\":4811,\"y\":5093},{\"x\":4811,\"y\":5283},{\"x\":4811,\"y\":4493},{\"x\":4811,\"y\":4503},{\"x\":3971,\"y\":5363},{\"x\":4811,\"y\":5103},{\"x\":4811,\"y\":4723},{\"x\":4811,\"y\":4523},{\"x\":4811,\"y\":4563},{\"x\":4161,\"y\":6053},{\"x\":4151,\"y\":6053},{\"x\":3971,\"y\":5163},{\"x\":3971,\"y\":5353},{\"x\":4811,\"y\":4693},{\"x\":3971,\"y\":5173},{\"x\":3971,\"y\":3953},{\"x\":3971,\"y\":3943},{\"x\":4141,\"y\":6053},{\"x\":4811,\"y\":4753},{\"x\":3971,\"y\":4443},{\"x\":3971,\"y\":5343},{\"x\":3971,\"y\":5183},{\"x\":3971,\"y\":4513},{\"x\":3971,\"y\":5333},{\"x\":4811,\"y\":4773},{\"x\":3971,\"y\":4473},{\"x\":4101,\"y\":6053},{\"x\":4811,\"y\":5413},{\"x\":4091,\"y\":6053},{\"x\":3971,\"y\":5193},{\"x\":4811,\"y\":4813},{\"x\":4131,\"y\":6053},{\"x\":4081,\"y\":6053},{\"x\":3971,\"y\":3933},{\"x\":3971,\"y\":4483},{\"x\":3971,\"y\":5323},{\"x\":4811,\"y\":4763},{\"x\":4811,\"y\":4833},{\"x\":4811,\"y\":4803},{\"x\":3971,\"y\":4213},{\"x\":3971,\"y\":5203},{\"x\":4121,\"y\":6053},{\"x\":3971,\"y\":4203},{\"x\":3971,\"y\":5213},{\"x\":3971,\"y\":5313},{\"x\":3971,\"y\":3903},{\"x\":4111,\"y\":6053},{\"x\":3971,\"y\":4283},{\"x\":3971,\"y\":5223},{\"x\":4071,\"y\":6053},{\"x\":3971,\"y\":5303},{\"x\":4811,\"y\":5403},{\"x\":3971,\"y\":4293},{\"x\":3971,\"y\":4433},{\"x\":4811,\"y\":4783},{\"x\":4061,\"y\":6053},{\"x\":4811,\"y\":4823},{\"x\":3971,\"y\":5233},{\"x\":4051,\"y\":6053},{\"x\":3971,\"y\":3923},{\"x\":3971,\"y\":4463},{\"x\":4041,\"y\":6053},{\"x\":4811,\"y\":5393},{\"x\":3971,\"y\":5293},{\"x\":3971,\"y\":3913},{\"x\":4811,\"y\":4793},{\"x\":4031,\"y\":6053},{\"x\":4811,\"y\":4923},{\"x\":4021,\"y\":6053},{\"x\":4811,\"y\":4913},{\"x\":3971,\"y\":5243},{\"x\":3971,\"y\":4183},{\"x\":3971,\"y\":4303},{\"x\":4811,\"y\":5613},{\"x\":4811,\"y\":5583},{\"x\":3971,\"y\":5283},{\"x\":3971,\"y\":3893},{\"x\":3971,\"y\":5273},{\"x\":4811,\"y\":5603},{\"x\":4571,\"y\":6053},{\"x\":4811,\"y\":5383},{\"x\":3971,\"y\":4313},{\"x\":3971,\"y\":5263},{\"x\":3971,\"y\":4273},{\"x\":3971,\"y\":4193},{\"x\":4811,\"y\":4843},{\"x\":4011,\"y\":6053},{\"x\":4531,\"y\":6053},{\"x\":3971,\"y\":5253},{\"x\":3971,\"y\":4783},{\"x\":3971,\"y\":4453},{\"x\":4501,\"y\":6053},{\"x\":4551,\"y\":6053},{\"x\":4001,\"y\":6053},{\"x\":3971,\"y\":4993},{\"x\":4811,\"y\":5373},{\"x\":4701,\"y\":6053},{\"x\":3971,\"y\":4263},{\"x\":3971,\"y\":4793},{\"x\":4521,\"y\":6053},{\"x\":4491,\"y\":6053},{\"x\":3971,\"y\":6023},{\"x\":4561,\"y\":6053},{\"x\":3971,\"y\":4343},{\"x\":3971,\"y\":4983},{\"x\":3971,\"y\":3883},{\"x\":3971,\"y\":6013},{\"x\":3971,\"y\":4503},{\"x\":3971,\"y\":4803},{\"x\":3971,\"y\":4973},{\"x\":4811,\"y\":5593},{\"x\":4511,\"y\":6053},{\"x\":3971,\"y\":4813},{\"x\":3971,\"y\":6003},{\"x\":4541,\"y\":6053},{\"x\":3971,\"y\":4493},{\"x\":3971,\"y\":4323},{\"x\":4691,\"y\":6053},{\"x\":3971,\"y\":4253},{\"x\":3971,\"y\":4423},{\"x\":4811,\"y\":4853},{\"x\":3971,\"y\":4413},{\"x\":3971,\"y\":5993},{\"x\":3971,\"y\":5953},{\"x\":3971,\"y\":4523},{\"x\":3971,\"y\":4963},{\"x\":4581,\"y\":6053},{\"x\":3971,\"y\":5963},{\"x\":3971,\"y\":4823},{\"x\":3971,\"y\":4953},{\"x\":3971,\"y\":4833},{\"x\":4811,\"y\":5273},{\"x\":4811,\"y\":5113},{\"x\":3971,\"y\":4943},{\"x\":3971,\"y\":4403},{\"x\":4811,\"y\":4903},{\"x\":3971,\"y\":4533},{\"x\":4681,\"y\":6053},{\"x\":4811,\"y\":5453},{\"x\":4671,\"y\":6053},{\"x\":3971,\"y\":4843},{\"x\":4811,\"y\":5263},{\"x\":4601,\"y\":6053},{\"x\":3971,\"y\":4353},{\"x\":4811,\"y\":5123},{\"x\":4661,\"y\":6053},{\"x\":3971,\"y\":4393},{\"x\":3971,\"y\":5983},{\"x\":3971,\"y\":4933},{\"x\":3971,\"y\":4383},{\"x\":3991,\"y\":6053},{\"x\":3971,\"y\":4853},{\"x\":3971,\"y\":4373},{\"x\":3971,\"y\":4923},{\"x\":3971,\"y\":3873},{\"x\":4591,\"y\":6053},{\"x\":4811,\"y\":5363},{\"x\":3971,\"y\":4333},{\"x\":3971,\"y\":4363},{\"x\":4811,\"y\":5253},{\"x\":4811,\"y\":5003},{\"x\":3971,\"y\":5973},{\"x\":4811,\"y\":4573},{\"x\":4811,\"y\":5133},{\"x\":4651,\"y\":6053},{\"x\":4801,\"y\":6053},{\"x\":4811,\"y\":4583},{\"x\":3971,\"y\":4863},{\"x\":4611,\"y\":6053},{\"x\":3971,\"y\":4643},{\"x\":3971,\"y\":4913},{\"x\":3971,\"y\":4653},{\"x\":3971,\"y\":4633},{\"x\":3971,\"y\":4873},{\"x\":3981,\"y\":6053},{\"x\":4811,\"y\":5013},{\"x\":3971,\"y\":4073},{\"x\":3971,\"y\":4223},{\"x\":4811,\"y\":5353},{\"x\":4641,\"y\":6053},{\"x\":3971,\"y\":4083},{\"x\":4811,\"y\":4873},{\"x\":4811,\"y\":3853},{\"x\":4811,\"y\":4593},{\"x\":3971,\"y\":4903},{\"x\":4791,\"y\":6053},{\"x\":3971,\"y\":3863},{\"x\":4811,\"y\":5023},{\"x\":4811,\"y\":4863},{\"x\":4811,\"y\":5243},{\"x\":4811,\"y\":5343},{\"x\":4811,\"y\":5143},{\"x\":3971,\"y\":4663},{\"x\":3971,\"y\":4883},{\"x\":3971,\"y\":4893},{\"x\":4811,\"y\":4883},{\"x\":3971,\"y\":6043},{\"x\":3971,\"y\":6033},{\"x\":3971,\"y\":4233},{\"x\":4811,\"y\":5933},{\"x\":4781,\"y\":6053},{\"x\":4811,\"y\":5943},{\"x\":4421,\"y\":6053},{\"x\":4771,\"y\":6053},{\"x\":4811,\"y\":5953},{\"x\":4811,\"y\":5233},{\"x\":4811,\"y\":6043},{\"x\":4811,\"y\":4893},{\"x\":4811,\"y\":5153},{\"x\":4811,\"y\":5963},{\"x\":4761,\"y\":6053},{\"x\":4811,\"y\":5223},{\"x\":3971,\"y\":4063},{\"x\":4811,\"y\":5163},{\"x\":3971,\"y\":4623},{\"x\":4631,\"y\":6053},{\"x\":4811,\"y\":5213},{\"x\":4811,\"y\":6033},{\"x\":4811,\"y\":5173},{\"x\":4811,\"y\":5203},{\"x\":4811,\"y\":5973},{\"x\":4811,\"y\":5183},{\"x\":4811,\"y\":5493},{\"x\":4811,\"y\":6023},{\"x\":3971,\"y\":3853},{\"x\":4811,\"y\":5813},{\"x\":4811,\"y\":5983},{\"x\":4811,\"y\":5193},{\"x\":3971,\"y\":4243},{\"x\":4811,\"y\":6013},{\"x\":3971,\"y\":4613},{\"x\":4811,\"y\":5993},{\"x\":4811,\"y\":6003},{\"x\":4621,\"y\":6053},{\"x\":4811,\"y\":5823},{\"x\":4811,\"y\":5833},{\"x\":4401,\"y\":6053},{\"x\":4711,\"y\":6053},{\"x\":4481,\"y\":6053},{\"x\":4811,\"y\":5473},{\"x\":4751,\"y\":6053},{\"x\":4811,\"y\":5503},{\"x\":4811,\"y\":5573},{\"x\":4811,\"y\":5533},{\"x\":4471,\"y\":6053},{\"x\":4811,\"y\":3843},{\"x\":4811,\"y\":5523},{\"x\":4741,\"y\":6053},{\"x\":4811,\"y\":5483},{\"x\":4811,\"y\":5543},{\"x\":4811,\"y\":3833},{\"x\":4461,\"y\":6053},{\"x\":4811,\"y\":5863},{\"x\":4451,\"y\":6053},{\"x\":4731,\"y\":6053},{\"x\":4811,\"y\":5853},{\"x\":4411,\"y\":6053},{\"x\":4441,\"y\":6053},{\"x\":4811,\"y\":5513},{\"x\":4811,\"y\":5803},{\"x\":3971,\"y\":3843},{\"x\":4721,\"y\":6053},{\"x\":4341,\"y\":6053},{\"x\":4811,\"y\":5563},{\"x\":4811,\"y\":5463},{\"x\":4351,\"y\":6053},{\"x\":4361,\"y\":6053},{\"x\":4371,\"y\":6053},{\"x\":4811,\"y\":5843},{\"x\":4811,\"y\":5753},{\"x\":4811,\"y\":5553},{\"x\":4811,\"y\":5783},{\"x\":4811,\"y\":5773},{\"x\":3971,\"y\":3833},{\"x\":4811,\"y\":5763},{\"x\":4811,\"y\":5793},{\"x\":4381,\"y\":6053},{\"x\":4811,\"y\":5873},{\"x\":4811,\"y\":6053},{\"x\":3971,\"y\":3823},{\"x\":4811,\"y\":5743},{\"x\":4811,\"y\":3823},{\"x\":4811,\"y\":5883},{\"x\":4391,\"y\":6053},{\"x\":4811,\"y\":5893},{\"x\":4811,\"y\":3813},{\"x\":3971,\"y\":3813},{\"x\":4811,\"y\":5913},{\"x\":4811,\"y\":5923},{\"x\":4811,\"y\":3793},{\"x\":4811,\"y\":5903},{\"x\":4811,\"y\":3803},{\"x\":4811,\"y\":5623},{\"x\":3971,\"y\":3803},{\"x\":4811,\"y\":5723},{\"x\":4811,\"y\":3783},{\"x\":3971,\"y\":3793},{\"x\":4811,\"y\":5653},{\"x\":4811,\"y\":5673},{\"x\":4811,\"y\":5713},{\"x\":4811,\"y\":5633},{\"x\":4811,\"y\":5683},{\"x\":4811,\"y\":5643},{\"x\":4811,\"y\":5663},{\"x\":4811,\"y\":5733},{\"x\":4431,\"y\":6053},{\"x\":4811,\"y\":5693},{\"x\":3971,\"y\":3783},{\"x\":4811,\"y\":5703},{\"x\":4331,\"y\":6053},{\"x\":3971,\"y\":5013},{\"x\":4811,\"y\":5443},{\"x\":3971,\"y\":5023},{\"x\":4161,\"y\":3773},{\"x\":4151,\"y\":3773},{\"x\":4141,\"y\":3773},{\"x\":4131,\"y\":3773},{\"x\":4811,\"y\":4933},{\"x\":4121,\"y\":3773},{\"x\":3971,\"y\":5033},{\"x\":4111,\"y\":3773},{\"x\":4091,\"y\":3773},{\"x\":4101,\"y\":3773},{\"x\":4811,\"y\":4943},{\"x\":4081,\"y\":3773},{\"x\":4811,\"y\":4273},{\"x\":4071,\"y\":3773},{\"x\":3971,\"y\":5043},{\"x\":4061,\"y\":3773},{\"x\":4811,\"y\":4953},{\"x\":4041,\"y\":3773},{\"x\":4051,\"y\":3773},{\"x\":4031,\"y\":3773},{\"x\":4181,\"y\":3773},{\"x\":4191,\"y\":3773},{\"x\":4811,\"y\":4263},{\"x\":4021,\"y\":3773},{\"x\":3971,\"y\":5053},{\"x\":4201,\"y\":3773},{\"x\":4011,\"y\":3773},{\"x\":4811,\"y\":4963},{\"x\":4811,\"y\":4253},{\"x\":4001,\"y\":3773},{\"x\":3981,\"y\":3773},{\"x\":3991,\"y\":3773},{\"x\":4811,\"y\":4973},{\"x\":4171,\"y\":3773},{\"x\":4811,\"y\":4243},{\"x\":3971,\"y\":5063},{\"x\":4811,\"y\":3863},{\"x\":4811,\"y\":4983},{\"x\":4811,\"y\":3873},{\"x\":4811,\"y\":4233},{\"x\":3971,\"y\":5073},{\"x\":4811,\"y\":4993},{\"x\":4811,\"y\":3883},{\"x\":4811,\"y\":4223},{\"x\":3971,\"y\":5083},{\"x\":4811,\"y\":3893},{\"x\":3971,\"y\":6053},{\"x\":4811,\"y\":3903},{\"x\":3971,\"y\":5093},{\"x\":4811,\"y\":4213},{\"x\":4811,\"y\":3913},{\"x\":4811,\"y\":4203},{\"x\":4811,\"y\":3923},{\"x\":4811,\"y\":3933},{\"x\":4811,\"y\":4193},{\"x\":4811,\"y\":3943},{\"x\":4811,\"y\":4183},{\"x\":4811,\"y\":3953},{\"x\":4811,\"y\":4173},{\"x\":4811,\"y\":3963},{\"x\":4811,\"y\":4163},{\"x\":4811,\"y\":3973},{\"x\":4811,\"y\":4153},{\"x\":4811,\"y\":3983},{\"x\":4811,\"y\":3993},{\"x\":4811,\"y\":4143},{\"x\":4811,\"y\":4003},{\"x\":4811,\"y\":4133},{\"x\":4811,\"y\":4013},{\"x\":4811,\"y\":4123},{\"x\":4811,\"y\":4023},{\"x\":4811,\"y\":4113},{\"x\":4811,\"y\":4033},{\"x\":4811,\"y\":4103},{\"x\":4811,\"y\":4043},{\"x\":4811,\"y\":4093},{\"x\":4811,\"y\":4053},{\"x\":4811,\"y\":4083},{\"x\":4811,\"y\":4073},{\"x\":4811,\"y\":4063},{\"x\":3971,\"y\":4593},{\"x\":3971,\"y\":4053},{\"x\":3971,\"y\":4543},{\"x\":3971,\"y\":4553},{\"x\":3971,\"y\":4033},{\"x\":3971,\"y\":4603},{\"x\":3971,\"y\":4563},{\"x\":3971,\"y\":4573},{\"x\":3971,\"y\":4043},{\"x\":4811,\"y\":4603},{\"x\":3971,\"y\":4143},{\"x\":3971,\"y\":4103},{\"x\":3971,\"y\":4583},{\"x\":3971,\"y\":4153},{\"x\":3971,\"y\":4113},{\"x\":4811,\"y\":4613},{\"x\":3971,\"y\":4673},{\"x\":3971,\"y\":4133},{\"x\":3971,\"y\":4023},{\"x\":3971,\"y\":4773},{\"x\":3971,\"y\":4763},{\"x\":3971,\"y\":4123},{\"x\":3971,\"y\":4093},{\"x\":3971,\"y\":4173},{\"x\":3971,\"y\":4013},{\"x\":3971,\"y\":4733},{\"x\":4811,\"y\":4623},{\"x\":3971,\"y\":4743},{\"x\":3971,\"y\":4163},{\"x\":4811,\"y\":3773},{\"x\":3971,\"y\":5503},{\"x\":3971,\"y\":5513},{\"x\":3971,\"y\":5523},{\"x\":4801,\"y\":3773},{\"x\":3971,\"y\":5493},{\"x\":3971,\"y\":5533},{\"x\":4791,\"y\":3773},{\"x\":4771,\"y\":3773},{\"x\":3971,\"y\":5483},{\"x\":4781,\"y\":3773},{\"x\":3971,\"y\":5543},{\"x\":4761,\"y\":3773},{\"x\":3971,\"y\":5473},{\"x\":3971,\"y\":5553},{\"x\":4751,\"y\":3773},{\"x\":4211,\"y\":3773},{\"x\":4221,\"y\":3773},{\"x\":3971,\"y\":5563},{\"x\":4241,\"y\":3773},{\"x\":4231,\"y\":3773},{\"x\":4251,\"y\":3773},{\"x\":3971,\"y\":5463},{\"x\":4261,\"y\":3773},{\"x\":3971,\"y\":5573},{\"x\":4741,\"y\":3773},{\"x\":4271,\"y\":3773},{\"x\":4731,\"y\":3773},{\"x\":4281,\"y\":3773},{\"x\":3971,\"y\":5583},{\"x\":3971,\"y\":5453},{\"x\":3971,\"y\":5603},{\"x\":3971,\"y\":5593},{\"x\":4291,\"y\":3773},{\"x\":4721,\"y\":3773},{\"x\":3971,\"y\":5613},{\"x\":4711,\"y\":3773},{\"x\":3971,\"y\":5443},{\"x\":4301,\"y\":3773},{\"x\":3971,\"y\":5623},{\"x\":4701,\"y\":3773},{\"x\":4311,\"y\":3773},{\"x\":3971,\"y\":5633},{\"x\":3971,\"y\":5943},{\"x\":3971,\"y\":5433},{\"x\":4691,\"y\":3773},{\"x\":4321,\"y\":3773},{\"x\":3971,\"y\":5643},{\"x\":3971,\"y\":5933},{\"x\":3971,\"y\":5923},{\"x\":3971,\"y\":5653},{\"x\":4331,\"y\":3773},{\"x\":4681,\"y\":3773},{\"x\":3971,\"y\":5913},{\"x\":3971,\"y\":5663},{\"x\":3971,\"y\":5423},{\"x\":3971,\"y\":5673},{\"x\":4341,\"y\":3773},{\"x\":3971,\"y\":5903},{\"x\":4671,\"y\":3773},{\"x\":3971,\"y\":5893},{\"x\":3971,\"y\":5683},{\"x\":4351,\"y\":3773},{\"x\":3971,\"y\":5883},{\"x\":3971,\"y\":5693},{\"x\":4661,\"y\":3773},{\"x\":4361,\"y\":3773},{\"x\":3971,\"y\":5873},{\"x\":3971,\"y\":5863},{\"x\":4371,\"y\":3773},{\"x\":4651,\"y\":3773},{\"x\":3971,\"y\":5853},{\"x\":3971,\"y\":5703},{\"x\":3971,\"y\":5843},{\"x\":3971,\"y\":5713},{\"x\":4381,\"y\":3773},{\"x\":4641,\"y\":3773},{\"x\":3971,\"y\":5833},{\"x\":3971,\"y\":5723},{\"x\":3971,\"y\":5823},{\"x\":3971,\"y\":5733},{\"x\":3971,\"y\":5813},{\"x\":3971,\"y\":5783},{\"x\":4391,\"y\":3773},{\"x\":3971,\"y\":5743},{\"x\":3971,\"y\":5763},{\"x\":3971,\"y\":5773},{\"x\":3971,\"y\":5803},{\"x\":4631,\"y\":3773},{\"x\":3971,\"y\":5753},{\"x\":3971,\"y\":5793},{\"x\":4401,\"y\":3773},{\"x\":4621,\"y\":3773},{\"x\":4411,\"y\":3773},{\"x\":4611,\"y\":3773},{\"x\":4421,\"y\":3773},{\"x\":4601,\"y\":3773},{\"x\":4431,\"y\":3773},{\"x\":4591,\"y\":3773},{\"x\":4441,\"y\":3773},{\"x\":4581,\"y\":3773},{\"x\":4451,\"y\":3773},{\"x\":4571,\"y\":3773},{\"x\":4461,\"y\":3773},{\"x\":4561,\"y\":3773},{\"x\":4471,\"y\":3773},{\"x\":4551,\"y\":3773},{\"x\":4481,\"y\":3773},{\"x\":4541,\"y\":3773},{\"x\":4491,\"y\":3773},{\"x\":4531,\"y\":3773},{\"x\":4521,\"y\":3773},{\"x\":4501,\"y\":3773},{\"x\":4511,\"y\":3773}],\"volumes\":[10,10,10,10,10,10,10,10,10,10,10,10,10,10,10,10,10,10,10,10,10,10,10,10,10,10,10,10,10,10,10,10,10,10,10,10,10,10,10,10,10,10,10,10,10,10,10,10,10,10,10,10,10,10,10,10,10,10,10,10,10,10,10,10,10,10,10,10,10,10,10,10,10,10,10,10,10,10,10,10,10,10,10,10,10,10,10,10,10,10,10,10,10,10,10,10,10,10,10,10,10,10,10,10,10,10,10,10,10,10,10,10,10,10,10,10,10,10,10,10,10,10,10,10,10,10,10,10,10,10,10,10,10,10,10,10,10,10,10,10,10,10,10,10,10,10,10,10,10,10,10,10,10,10,10,10,10,10,10,10,10,10,10,10,10,10,10,10,10,10,10,10,10,10,10,10,10,10,10,10,10,10,10,10,10,10,10,10,10,10,10,10,10,10,10,10,10,10,10,10,10,10,10,10,10,10,10,10,10,10,10,10,10,10,10,10,10,10,10,10,10,10,10,10,10,10,10,10,10,10,10,10,10,10,10,10,10,10,10,10,10,10,10,10,10,10,10,10,10,10,10,10,10,10,10,10,10,10,10,10,10,10,10,10,10,10,10,10,10,10,10,10,10,10,10,10,10,10,10,10,10,10,10,10,10,10,10,10,10,10,10,10,10,10,10,10,10,10,10,10,10,10,10,10,10,10,10,10,10,10,10,10,10,10,10,10,10,10,10,10,10,10,10,10,10,10,10,10,10,10,10,10,10,10,10,10,10,10,10,10,10,10,10,10,10,10,10,10,10,10,10,10,10,10,10,10,10,10,10,10,10,10,10,10,10,10,10,10,10,10,10,10,10,10,10,10,10,10,10,10,10,10,10,10,10,10,10,10,10,10,10,10,10,10,10,10,10,10,10,10,10,10,10,10,10,10,10,10,10,10,10,10,10,10,10,10,10,10,10,10,10,10,10,10,10,10,10,10,10,10,10,10,10,10,10,10,10,10,10,10,10,10,10,10,10,10,10,10,10,10,10,10,10,10,10,10,10,10,10,10,10,10,10,10,10,10,10,10,10,10,10,10,10,10,10,10,10,10,10,10,10,10,10,10,10,10,10,10,10,10,10,10,10,10,10,10,10,10,10,10,10,10,10,10,10,10,10,10,10,10,10,10,10,10,10,10,10,10,10,10,10,10,10,10,10,10,10,10,10,10,10,10,10,10,10,10,10,10,10,10,10,10,10,10,10,10,10,10,10,10,10,10,10,10,10,10,10,10,10,10,10,10,10,10,10,10,10,10,10,10,10,10,10,10,10,10,10,10,10,10,10,10,10,10,10,10,10,10,10,10,10,10,10,10,10,10,10,10,10,10,10,10,10,10,10,10,10,10,10,10,10,10,10,10,10,10,10,10,10,10,10,10,10,10]}"}}