{"Success":{"submission":{"_id":"64abcaa867169bacdb5f2c95","problem_id":36,"user_id":"64a3a7de8c685313d1c60d9d","score":{"Success":346530560.0},"submitted_at":"2023-07-10T09:08:56.255518350Z"},"contents":"{\"placements\":[{\"x\":1255,\"y\":776},{\"x\":1255,\"y\":726},{\"x\":1005,\"y\":936},{\"x\":1255,\"y\":736},{\"x\":1005,\"y\":726},{\"x\":1045,\"y\":626},{\"x\":1255,\"y\":926},{\"x\":1005,\"y\":906},{\"x\":1085,\"y\":626},{\"x\":1045,\"y\":936},{\"x\":1255,\"y\":846},{\"x\":1175,\"y\":936},{\"x\":1065,\"y\":626},{\"x\":1255,\"y\":816},{\"x\":1255,\"y\":826},{\"x\":1125,\"y\":626},{\"x\":1005,\"y\":666},{\"x\":1005,\"y\":716},{\"x\":1255,\"y\":746},{\"x\":1255,\"y\":656},{\"x\":1005,\"y\":886},{\"x\":1225,\"y\":936},{\"x\":1005,\"y\":816},{\"x\":1075,\"y\":936},{\"x\":1085,\"y\":936},{\"x\":1255,\"y\":716},{\"x\":1255,\"y\":806},{\"x\":1255,\"y\":896},{\"x\":1005,\"y\":896},{\"x\":1255,\"y\":636},{\"x\":1005,\"y\":926},{\"x\":1005,\"y\":826},{\"x\":1035,\"y\":626},{\"x\":1005,\"y\":676},{\"x\":1005,\"y\":836},{\"x\":1005,\"y\":736},{\"x\":1255,\"y\":906},{\"x\":1065,\"y\":936},{\"x\":1255,\"y\":876},{\"x\":1255,\"y\":766},{\"x\":1255,\"y\":916},{\"x\":1005,\"y\":776},{\"x\":1005,\"y\":706},{\"x\":1005,\"y\":786},{\"x\":1215,\"y\":936},{\"x\":1025,\"y\":936},{\"x\":1005,\"y\":656},{\"x\":1135,\"y\":626},{\"x\":1255,\"y\":686},{\"x\":1005,\"y\":806},{\"x\":1005,\"y\":626},{\"x\":1255,\"y\":626},{\"x\":1155,\"y\":936},{\"x\":1255,\"y\":836},{\"x\":1005,\"y\":686},{\"x\":1255,\"y\":756},{\"x\":1165,\"y\":936},{\"x\":1035,\"y\":936},{\"x\":1255,\"y\":646},{\"x\":1025,\"y\":626},{\"x\":1255,\"y\":866},{\"x\":1005,\"y\":866},{\"x\":1095,\"y\":626},{\"x\":1255,\"y\":696},{\"x\":1005,\"y\":876},{\"x\":1055,\"y\":626},{\"x\":1005,\"y\":796},{\"x\":1005,\"y\":756},{\"x\":1005,\"y\":856},{\"x\":1005,\"y\":916},{\"x\":1105,\"y\":626},{\"x\":1205,\"y\":936},{\"x\":1255,\"y\":666},{\"x\":1015,\"y\":936},{\"x\":1005,\"y\":846},{\"x\":1255,\"y\":886},{\"x\":1075,\"y\":626},{\"x\":1185,\"y\":936},{\"x\":1255,\"y\":786},{\"x\":1015,\"y\":626},{\"x\":1005,\"y\":766},{\"x\":1235,\"y\":936},{\"x\":1005,\"y\":646},{\"x\":1195,\"y\":936},{\"x\":1245,\"y\":936},{\"x\":1115,\"y\":626},{\"x\":1055,\"y\":936},{\"x\":1005,\"y\":746},{\"x\":1255,\"y\":676},{\"x\":1005,\"y\":636},{\"x\":1255,\"y\":936},{\"x\":1255,\"y\":706},{\"x\":1255,\"y\":796},{\"x\":1255,\"y\":856},{\"x\":1005,\"y\":696}],\"volumes\":[10,10,10,10,10,10,10,10,10,10,10,10,10,10,10,10,10,10,10,10,10,10,10,10,0,10,10,10,10,10,10,10,10,10,10,10,10,10,10,10,10,10,10,10,10,10,10,10,10,10,10,10,10,10,10,0,10,10,10,10,10,10,10,10,10,10,10,10,10,10,10,10,10,10,10,10,10,10,10,10,10,10,10,10,10,10,10,10,10,10,10,10,10,10,10]}"}}