{"Success":{"submission":{"_id":"64ab6002dabcf421a98f24a4","problem_id":88,"user_id":"64a3a7de8c685313d1c60d9d","score":{"Success":31796236.0},"submitted_at":"2023-07-10T01:33:54.491491330Z"},"contents":"{\"placements\":[{\"x\":856,\"y\":447},{\"x\":896,\"y\":407},{\"x\":896,\"y\":337},{\"x\":726,\"y\":407},{\"x\":766,\"y\":457},{\"x\":786,\"y\":487},{\"x\":866,\"y\":437},{\"x\":866,\"y\":387},{\"x\":696,\"y\":387},{\"x\":836,\"y\":417},{\"x\":846,\"y\":477},{\"x\":856,\"y\":377},{\"x\":756,\"y\":337},{\"x\":876,\"y\":457},{\"x\":896,\"y\":377},{\"x\":786,\"y\":447},{\"x\":756,\"y\":457},{\"x\":826,\"y\":467},{\"x\":756,\"y\":487},{\"x\":816,\"y\":447},{\"x\":806,\"y\":437},{\"x\":776,\"y\":467},{\"x\":716,\"y\":427},{\"x\":796,\"y\":457},{\"x\":686,\"y\":347},{\"x\":806,\"y\":477},{\"x\":686,\"y\":357},{\"x\":866,\"y\":377},{\"x\":806,\"y\":337},{\"x\":856,\"y\":407},{\"x\":786,\"y\":357},{\"x\":846,\"y\":397},{\"x\":656,\"y\":327},{\"x\":856,\"y\":367},{\"x\":866,\"y\":367},{\"x\":886,\"y\":367},{\"x\":716,\"y\":417},{\"x\":676,\"y\":367},{\"x\":896,\"y\":387},{\"x\":886,\"y\":397},{\"x\":766,\"y\":487},{\"x\":886,\"y\":387},{\"x\":816,\"y\":427},{\"x\":886,\"y\":377},{\"x\":696,\"y\":347},{\"x\":716,\"y\":437},{\"x\":826,\"y\":437},{\"x\":696,\"y\":317},{\"x\":826,\"y\":487},{\"x\":776,\"y\":447},{\"x\":736,\"y\":367},{\"x\":906,\"y\":377},{\"x\":856,\"y\":357},{\"x\":746,\"y\":457},{\"x\":706,\"y\":347},{\"x\":866,\"y\":357},{\"x\":726,\"y\":377},{\"x\":766,\"y\":467},{\"x\":726,\"y\":397},{\"x\":676,\"y\":387},{\"x\":796,\"y\":437},{\"x\":896,\"y\":397},{\"x\":696,\"y\":377},{\"x\":836,\"y\":407},{\"x\":666,\"y\":347},{\"x\":786,\"y\":507},{\"x\":746,\"y\":437},{\"x\":866,\"y\":347},{\"x\":766,\"y\":447},{\"x\":846,\"y\":417},{\"x\":806,\"y\":447},{\"x\":856,\"y\":457},{\"x\":826,\"y\":417},{\"x\":716,\"y\":347},{\"x\":846,\"y\":387},{\"x\":856,\"y\":347},{\"x\":786,\"y\":437},{\"x\":886,\"y\":427},{\"x\":836,\"y\":457},{\"x\":896,\"y\":437},{\"x\":876,\"y\":417},{\"x\":716,\"y\":337},{\"x\":686,\"y\":327},{\"x\":886,\"y\":447},{\"x\":806,\"y\":427},{\"x\":836,\"y\":347},{\"x\":716,\"y\":327},{\"x\":786,\"y\":457},{\"x\":776,\"y\":437},{\"x\":656,\"y\":357},{\"x\":906,\"y\":417},{\"x\":876,\"y\":437},{\"x\":776,\"y\":487},{\"x\":836,\"y\":427},{\"x\":806,\"y\":497},{\"x\":666,\"y\":337},{\"x\":866,\"y\":337},{\"x\":866,\"y\":447},{\"x\":906,\"y\":387},{\"x\":836,\"y\":397},{\"x\":906,\"y\":407},{\"x\":726,\"y\":387},{\"x\":736,\"y\":417},{\"x\":706,\"y\":397},{\"x\":886,\"y\":337},{\"x\":856,\"y\":397},{\"x\":896,\"y\":347},{\"x\":726,\"y\":447},{\"x\":696,\"y\":397},{\"x\":846,\"y\":377},{\"x\":906,\"y\":397},{\"x\":856,\"y\":467},{\"x\":726,\"y\":427},{\"x\":816,\"y\":417},{\"x\":696,\"y\":357},{\"x\":796,\"y\":357},{\"x\":746,\"y\":367},{\"x\":836,\"y\":467},{\"x\":696,\"y\":367},{\"x\":646,\"y\":337},{\"x\":746,\"y\":337},{\"x\":816,\"y\":437},{\"x\":776,\"y\":457},{\"x\":726,\"y\":437},{\"x\":666,\"y\":327},{\"x\":796,\"y\":447},{\"x\":846,\"y\":447},{\"x\":676,\"y\":327},{\"x\":706,\"y\":337},{\"x\":766,\"y\":437},{\"x\":796,\"y\":427},{\"x\":796,\"y\":477},{\"x\":666,\"y\":367},{\"x\":856,\"y\":387},{\"x\":846,\"y\":407},{\"x\":826,\"y\":407},{\"x\":826,\"y\":427},{\"x\":846,\"y\":367},{\"x\":736,\"y\":377},{\"x\":656,\"y\":317},{\"x\":686,\"y\":377},{\"x\":816,\"y\":477},{\"x\":686,\"y\":397},{\"x\":676,\"y\":357},{\"x\":816,\"y\":467},{\"x\":756,\"y\":367},{\"x\":806,\"y\":357},{\"x\":786,\"y\":427},{\"x\":756,\"y\":447},{\"x\":676,\"y\":337},{\"x\":856,\"y\":437},{\"x\":866,\"y\":427},{\"x\":876,\"y\":407},{\"x\":706,\"y\":357},{\"x\":756,\"y\":467},{\"x\":886,\"y\":417},{\"x\":836,\"y\":387},{\"x\":886,\"y\":347},{\"x\":676,\"y\":347},{\"x\":816,\"y\":337},{\"x\":676,\"y\":307},{\"x\":806,\"y\":417},{\"x\":696,\"y\":337},{\"x\":796,\"y\":497},{\"x\":736,\"y\":407},{\"x\":746,\"y\":427},{\"x\":826,\"y\":457},{\"x\":706,\"y\":387},{\"x\":736,\"y\":387},{\"x\":686,\"y\":337},{\"x\":896,\"y\":427},{\"x\":836,\"y\":477},{\"x\":736,\"y\":457},{\"x\":766,\"y\":367},{\"x\":776,\"y\":427},{\"x\":756,\"y\":427},{\"x\":716,\"y\":407},{\"x\":736,\"y\":397},{\"x\":836,\"y\":337},{\"x\":706,\"y\":407},{\"x\":866,\"y\":457},{\"x\":846,\"y\":457},{\"x\":736,\"y\":437},{\"x\":876,\"y\":397},{\"x\":736,\"y\":447},{\"x\":846,\"y\":347},{\"x\":816,\"y\":487},{\"x\":746,\"y\":377},{\"x\":786,\"y\":477},{\"x\":816,\"y\":357},{\"x\":656,\"y\":347},{\"x\":696,\"y\":407},{\"x\":886,\"y\":357},{\"x\":806,\"y\":467},{\"x\":706,\"y\":367},{\"x\":876,\"y\":317},{\"x\":846,\"y\":357},{\"x\":766,\"y\":427},{\"x\":776,\"y\":507},{\"x\":776,\"y\":367},{\"x\":896,\"y\":357},{\"x\":716,\"y\":357},{\"x\":816,\"y\":407},{\"x\":686,\"y\":367},{\"x\":706,\"y\":377},{\"x\":706,\"y\":327},{\"x\":746,\"y\":417},{\"x\":756,\"y\":437},{\"x\":746,\"y\":387},{\"x\":876,\"y\":387},{\"x\":836,\"y\":447},{\"x\":756,\"y\":377},{\"x\":686,\"y\":317},{\"x\":766,\"y\":347},{\"x\":766,\"y\":497},{\"x\":826,\"y\":397},{\"x\":796,\"y\":417},{\"x\":786,\"y\":367},{\"x\":866,\"y\":417},{\"x\":736,\"y\":337},{\"x\":676,\"y\":377},{\"x\":746,\"y\":407},{\"x\":876,\"y\":367},{\"x\":836,\"y\":377},{\"x\":886,\"y\":317},{\"x\":876,\"y\":447},{\"x\":876,\"y\":377},{\"x\":886,\"y\":407},{\"x\":846,\"y\":437},{\"x\":806,\"y\":407},{\"x\":726,\"y\":357},{\"x\":886,\"y\":437},{\"x\":786,\"y\":417},{\"x\":826,\"y\":357},{\"x\":746,\"y\":397},{\"x\":776,\"y\":347},{\"x\":766,\"y\":377},{\"x\":856,\"y\":327},{\"x\":796,\"y\":367},{\"x\":826,\"y\":387},{\"x\":766,\"y\":417},{\"x\":756,\"y\":347},{\"x\":756,\"y\":387},{\"x\":706,\"y\":417},{\"x\":836,\"y\":357},{\"x\":896,\"y\":417},{\"x\":876,\"y\":427},{\"x\":726,\"y\":417},{\"x\":866,\"y\":327},{\"x\":846,\"y\":467},{\"x\":856,\"y\":427},{\"x\":746,\"y\":347},{\"x\":736,\"y\":357},{\"x\":666,\"y\":357},{\"x\":786,\"y\":347},{\"x\":816,\"y\":397},{\"x\":776,\"y\":477},{\"x\":896,\"y\":367},{\"x\":656,\"y\":337},{\"x\":746,\"y\":467},{\"x\":776,\"y\":417},{\"x\":786,\"y\":497},{\"x\":726,\"y\":337},{\"x\":756,\"y\":417},{\"x\":836,\"y\":367},{\"x\":796,\"y\":407},{\"x\":736,\"y\":347},{\"x\":826,\"y\":377},{\"x\":666,\"y\":317},{\"x\":806,\"y\":397},{\"x\":786,\"y\":407},{\"x\":816,\"y\":457},{\"x\":816,\"y\":387},{\"x\":826,\"y\":337},{\"x\":726,\"y\":347},{\"x\":796,\"y\":467},{\"x\":796,\"y\":347},{\"x\":846,\"y\":337},{\"x\":696,\"y\":327},{\"x\":806,\"y\":347},{\"x\":676,\"y\":317},{\"x\":716,\"y\":397},{\"x\":776,\"y\":407},{\"x\":746,\"y\":447},{\"x\":766,\"y\":407},{\"x\":866,\"y\":407},{\"x\":716,\"y\":367},{\"x\":886,\"y\":327},{\"x\":766,\"y\":477},{\"x\":876,\"y\":327},{\"x\":796,\"y\":397},{\"x\":686,\"y\":387},{\"x\":826,\"y\":367},{\"x\":876,\"y\":337},{\"x\":806,\"y\":387},{\"x\":876,\"y\":357},{\"x\":786,\"y\":397},{\"x\":776,\"y\":377},{\"x\":826,\"y\":447},{\"x\":826,\"y\":477},{\"x\":716,\"y\":387},{\"x\":756,\"y\":397},{\"x\":716,\"y\":377},{\"x\":876,\"y\":347},{\"x\":816,\"y\":377},{\"x\":816,\"y\":347},{\"x\":786,\"y\":467},{\"x\":746,\"y\":357},{\"x\":776,\"y\":397},{\"x\":806,\"y\":367},{\"x\":756,\"y\":357},{\"x\":756,\"y\":407},{\"x\":796,\"y\":387},{\"x\":866,\"y\":397},{\"x\":836,\"y\":437},{\"x\":806,\"y\":487},{\"x\":766,\"y\":387},{\"x\":786,\"y\":377},{\"x\":806,\"y\":457},{\"x\":816,\"y\":367},{\"x\":856,\"y\":337},{\"x\":766,\"y\":397},{\"x\":756,\"y\":477},{\"x\":856,\"y\":417},{\"x\":736,\"y\":427},{\"x\":766,\"y\":357},{\"x\":776,\"y\":387},{\"x\":846,\"y\":427},{\"x\":726,\"y\":367},{\"x\":826,\"y\":347},{\"x\":806,\"y\":377},{\"x\":776,\"y\":357},{\"x\":776,\"y\":497},{\"x\":796,\"y\":377},{\"x\":796,\"y\":487},{\"x\":786,\"y\":387}],\"volumes\":[10,10,10,10,10,10,10,10,10,10,10,10,10,10,10,10,10,10,10,10,10,10,10,10,10,10,10,10,10,10,10,10,10,10,10,10,10,10,10,10,10,10,10,10,10,10,10,10,10,10,10,10,10,10,10,10,10,10,10,10,10,10,10,10,10,10,10,10,10,10,10,10,10,10,10,10,10,10,10,10,10,10,10,10,10,10,10,10,10,10,10,10,10,10,10,10,10,10,10,10,10,10,10,10,10,10,10,10,10,10,10,10,10,10,10,10,10,10,10,10,10,10,10,10,10,10,10,10,10,10,10,10,10,10,10,10,10,10,10,10,10,10,10,10,10,10,10,10,10,10,10,10,10,10,10,10,10,10,10,10,10,10,10,10,10,10,10,10,10,10,10,10,10,10,10,10,10,10,10,10,10,10,10,10,10,10,10,10,10,10,10,10,10,10,10,10,10,10,10,10,10,10,10,10,10,10,10,10,10,10,10,10,10,10,10,10,10,10,10,10,10,10,10,10,10,10,10,10,10,10,10,10,10,10,10,10,10,10,10,10,10,10,10,10,10,10,10,10,10,10,10,10,10,10,10,10,10,10,10,10,10,10,10,10,10,10,10,10,10,10,10,10,10,10,10,10,10,10,10,10,10,10,10,10,10,10,10,10,10,10,10,10,10,10,10,10,10,10,10,10,10,10,10,10,10,10,10,10,10,10,10,10,10,10,10,10,10,10,10,10,10,10,10,10,10,10,10,10,10,10,10,10,10,10,10,10]}"}}